{
    "operations": {},
    "tasks": {
        "@taqueria/plugin-ligo.compile.1668506274640": {
            "task": "compile",
            "plugin": "@taqueria/plugin-ligo",
            "time": 1668506274640,
            "output": [
                {
                    "contract": "wallet_manager.mligo",
                    "artifact": "artifacts/wallet_manager.tz"
                },
                {
                    "contract": "smart_wallet.mligo",
                    "artifact": "artifacts/smart_wallet.tz"
                },
                {
                    "contract": "lumos_settings.mligo",
                    "artifact": "Not compiled"
                },
                {
                    "contract": "illuminate.mligo",
                    "artifact": "Not compiled"
                }
            ]
        },
        "@taqueria/plugin-ligo.compile.1668506311279": {
            "task": "compile",
            "plugin": "@taqueria/plugin-ligo",
            "time": 1668506311279,
            "output": [
                {
                    "contract": "wallet_manager.mligo",
                    "artifact": "artifacts/wallet_manager.tz"
                },
                {
                    "contract": "smart_wallet.mligo",
                    "artifact": "artifacts/smart_wallet.tz"
                },
                {
                    "contract": "lumos_settings.mligo",
                    "artifact": "Not compiled"
                },
                {
                    "contract": "illuminate.mligo",
                    "artifact": "Not compiled"
                }
            ]
        },
        "@taqueria/plugin-ligo.compile.1668506661587": {
            "task": "compile",
            "plugin": "@taqueria/plugin-ligo",
            "time": 1668506661587,
            "output": [
                {
                    "contract": "wallet_manager.mligo",
                    "artifact": "artifacts/wallet_manager.tz"
                },
                {
                    "contract": "smart_wallet.mligo",
                    "artifact": "artifacts/smart_wallet.tz"
                },
                {
                    "contract": "lumos_settings.mligo",
                    "artifact": "Not compiled"
                },
                {
                    "contract": "illuminate.mligo",
                    "artifact": "Not compiled"
                }
            ]
        },
        "@taqueria/plugin-ligo.compile.1668506734578": {
            "task": "compile",
            "plugin": "@taqueria/plugin-ligo",
            "time": 1668506734578,
            "output": [
                {
                    "contract": "wallet_manager.mligo",
                    "artifact": "artifacts/wallet_manager.tz"
                },
                {
                    "contract": "smart_wallet.mligo",
                    "artifact": "artifacts/smart_wallet.tz"
                },
                {
                    "contract": "lumos_settings.mligo",
                    "artifact": "Not compiled"
                },
                {
                    "contract": "illuminate.mligo",
                    "artifact": "Not compiled"
                }
            ]
        },
        "@taqueria/plugin-ligo.compile.1668506884514": {
            "task": "compile",
            "plugin": "@taqueria/plugin-ligo",
            "time": 1668506884515,
            "output": [
                {
                    "contract": "wallet_manager.mligo",
                    "artifact": "artifacts/wallet_manager.tz"
                },
                {
                    "contract": "smart_wallet.mligo",
                    "artifact": "artifacts/smart_wallet.tz"
                },
                {
                    "contract": "lumos_settings.mligo",
                    "artifact": "Not compiled"
                },
                {
                    "contract": "illuminate.mligo",
                    "artifact": "Not compiled"
                }
            ]
        }
    }
}